Metadata-Version: 2.1
Name: segf
Version: 1.0.4
Summary: Segmentation by Factorization
Home-page: https://github.com/deepathology/fseg
Author: Ofir Hadar, Jacob Gildenblat
Author-email: jacob.gildenblat@gmail.com
Project-URL: Bug Tracker, https://github.com/deepathology/fseg/issues
Classifier: Programming Language :: Python :: 3
Classifier: License :: OSI Approved :: MIT License
Classifier: Operating System :: OS Independent
Requires-Python: >=3.9
License-File: LICENSE
Requires-Dist: numpy
Requires-Dist: grad-cam
Requires-Dist: scikit-learn
Requires-Dist: pillow
Requires-Dist: matplotlib
Requires-Dist: torch
Requires-Dist: timm
Requires-Dist: huggingface_hub
Requires-Dist: joblib
Requires-Dist: opencv-python
